{
  "skeleton": {
    "hash": "/ah2ZLUsWrXYMmUKZiR0jHld3sQ",
    "spine": "3.8.86",
    "x": -215.45,
    "y": -215.45,
    "width": 430.9,
    "height": 430.9,
    "images": "",
    "audio": "E:/Svetlana/TTT/03_spine/t_hp2/../t_hp1"
  },
  "bones": [
    { "name": "root" },
    { "name": "stars", "parent": "root" },
    { "name": "rays", "parent": "stars", "length": 100, "rotation": -132.12 },
    { "name": "rays2", "parent": "stars", "length": 100 },
    { "name": "rays3", "parent": "stars", "length": 100, "rotation": 132.42 },
    { "name": "glow", "parent": "stars", "scaleX": 1.3, "scaleY": 1.3 },
    { "name": "star", "parent": "stars" },
    { "name": "star2", "parent": "stars" },
    { "name": "star3", "parent": "stars" },
    { "name": "star4", "parent": "stars" },
    { "name": "star5", "parent": "stars" },
    { "name": "star6", "parent": "stars" },
    { "name": "star7", "parent": "stars" },
    { "name": "star8", "parent": "stars", "color": "9f6969ff" },
    { "name": "star9", "parent": "stars", "color": "9f6969ff" },
    { "name": "star10", "parent": "stars", "color": "9f6969ff" },
    { "name": "star11", "parent": "stars", "color": "9f6969ff" },
    { "name": "star12", "parent": "stars", "color": "9f6969ff" },
    { "name": "star13", "parent": "stars", "color": "9f6969ff" },
    { "name": "star14", "parent": "stars", "color": "9f6969ff" }
  ],
  "slots": [
    {
      "name": "glow",
      "bone": "glow",
      "color": "d1f51b00",
      "attachment": "glow",
      "blend": "additive"
    },
    {
      "name": "rays",
      "bone": "rays",
      "color": "ffffff00",
      "attachment": "rays",
      "blend": "additive"
    },
    {
      "name": "rays2",
      "bone": "rays2",
      "color": "ffffff00",
      "attachment": "rays",
      "blend": "additive"
    },
    {
      "name": "rays3",
      "bone": "rays3",
      "color": "ffffff00",
      "attachment": "rays",
      "blend": "additive"
    },
    { "name": "star", "bone": "star", "attachment": "star" },
    { "name": "star8", "bone": "star8", "attachment": "star" },
    { "name": "star2", "bone": "star2", "attachment": "star" },
    { "name": "star9", "bone": "star9", "attachment": "star" },
    { "name": "star3", "bone": "star3", "attachment": "star" },
    { "name": "star10", "bone": "star10", "attachment": "star" },
    { "name": "star4", "bone": "star4", "attachment": "star" },
    { "name": "star11", "bone": "star11", "attachment": "star" },
    { "name": "star7", "bone": "star7", "attachment": "star" },
    { "name": "star14", "bone": "star14", "attachment": "star" },
    { "name": "star5", "bone": "star5", "attachment": "star" },
    { "name": "star12", "bone": "star12", "attachment": "star" },
    { "name": "star6", "bone": "star6", "attachment": "star" },
    { "name": "star13", "bone": "star13", "attachment": "star" }
  ],
  "skins": [
    {
      "name": "default",
      "attachments": {
        "glow": {
          "glow": { "x": -2.44, "y": -0.57, "width": 256, "height": 256 }
        },
        "rays": { "rays": { "width": 305, "height": 305 } },
        "rays2": { "rays": { "width": 305, "height": 305 } },
        "rays3": { "rays": { "width": 305, "height": 305 } },
        "star": { "star": { "width": 40, "height": 42 } },
        "star10": {
          "star": { "scaleX": 0.8, "scaleY": 0.8, "width": 40, "height": 42 }
        },
        "star11": {
          "star": { "scaleX": 0.6, "scaleY": 0.6, "width": 40, "height": 42 }
        },
        "star12": {
          "star": { "scaleX": 0.76, "scaleY": 0.76, "width": 40, "height": 42 }
        },
        "star13": {
          "star": { "scaleX": 0.4, "scaleY": 0.4, "width": 40, "height": 42 }
        },
        "star14": {
          "star": { "scaleX": 0.9, "scaleY": 0.9, "width": 40, "height": 42 }
        },
        "star2": {
          "star": { "scaleX": 0.8, "scaleY": 0.8, "width": 40, "height": 42 }
        },
        "star3": {
          "star": { "scaleX": 0.8, "scaleY": 0.8, "width": 40, "height": 42 }
        },
        "star4": {
          "star": { "scaleX": 0.6, "scaleY": 0.6, "width": 40, "height": 42 }
        },
        "star5": {
          "star": { "scaleX": 0.76, "scaleY": 0.76, "width": 40, "height": 42 }
        },
        "star6": {
          "star": { "scaleX": 0.4, "scaleY": 0.4, "width": 40, "height": 42 }
        },
        "star7": {
          "star": { "scaleX": 0.9, "scaleY": 0.9, "width": 40, "height": 42 }
        },
        "star8": { "star": { "width": 40, "height": 42 } },
        "star9": {
          "star": { "scaleX": 0.8, "scaleY": 0.8, "width": 40, "height": 42 }
        }
      }
    }
  ],
  "animations": {
    "win": {
      "slots": {
        "glow": {
          "color": [
            { "time": 0.1667, "color": "d1f51b00", "curve": 0.25, "c3": 0.75 },
            { "time": 0.4667, "color": "d2f51cff", "curve": "stepped" },
            { "time": 1, "color": "d2f51cff", "curve": 0.25, "c3": 0.75 },
            { "time": 1.3333, "color": "d1f51b00" }
          ]
        },
        "rays": {
          "color": [
            { "color": "ffffff00" },
            { "time": 0.2667, "color": "ffffffff" },
            { "time": 0.5667, "color": "ffffff00" },
            { "time": 0.6, "color": "ffffffff", "curve": "stepped" },
            { "time": 0.8667, "color": "ffffffff" },
            { "time": 1.1667, "color": "ffffff00" }
          ]
        },
        "rays2": {
          "color": [
            { "time": 0.1667, "color": "ffffff00" },
            { "time": 0.3333, "color": "ffffffff", "curve": "stepped" },
            { "time": 0.4333, "color": "ffffffff" },
            { "time": 0.7333, "color": "ffffff00" },
            { "time": 0.7667, "color": "ffffffff", "curve": "stepped" },
            { "time": 0.8667, "color": "ffffffff" },
            { "time": 1.2333, "color": "ffffff00" }
          ]
        },
        "rays3": {
          "color": [
            { "time": 0.3333, "color": "ffffffff", "curve": "stepped" },
            { "time": 0.6, "color": "ffffffff" },
            { "time": 0.9, "color": "ffffff00" }
          ]
        },
        "star": {
          "color": [
            { "color": "ffffff00", "curve": "stepped" },
            { "time": 0.1667, "color": "ffffff00" },
            { "time": 0.3333, "color": "ffffffff", "curve": "stepped" },
            { "time": 0.5667, "color": "ffffffff" },
            { "time": 0.8333, "color": "ffffff00" }
          ]
        },
        "star2": {
          "color": [
            { "color": "ffffff00" },
            { "time": 0.1667, "color": "ffffffff", "curve": "stepped" },
            { "time": 0.4, "color": "ffffffff" },
            { "time": 0.6667, "color": "ffffff00" },
            { "time": 0.7, "color": "ffffffff", "curve": "stepped" },
            { "time": 1.1, "color": "ffffffff" },
            { "time": 1.3667, "color": "ffffff00" }
          ]
        },
        "star3": {
          "color": [
            { "color": "ffffff00", "curve": "stepped" },
            { "time": 0.2333, "color": "ffffff00" },
            { "time": 0.4, "color": "ffffffff", "curve": "stepped" },
            { "time": 0.6333, "color": "ffffffff" },
            { "time": 0.9, "color": "ffffff00" }
          ]
        },
        "star4": {
          "color": [
            { "color": "ffffff00", "curve": "stepped" },
            { "time": 0.5, "color": "ffffff00" },
            { "time": 0.6667, "color": "ffffffff", "curve": "stepped" },
            { "time": 0.9, "color": "ffffffff" },
            { "time": 1.1667, "color": "ffffff00" }
          ]
        },
        "star5": {
          "color": [
            { "color": "ffffff00", "curve": "stepped" },
            { "time": 0.4, "color": "ffffff00" },
            { "time": 0.5667, "color": "ffffffff", "curve": "stepped" },
            { "time": 0.8, "color": "ffffffff" },
            { "time": 1.0667, "color": "ffffff00" }
          ]
        },
        "star6": {
          "color": [
            { "color": "ffffff00", "curve": "stepped" },
            { "time": 0.5, "color": "ffffff00" },
            { "time": 0.6667, "color": "ffffffff", "curve": "stepped" },
            { "time": 0.9, "color": "ffffffff" },
            { "time": 1.1667, "color": "ffffff00" }
          ]
        },
        "star7": {
          "color": [
            { "color": "ffffff00", "curve": "stepped" },
            { "time": 0.3333, "color": "ffffff00" },
            { "time": 0.5, "color": "ffffffff", "curve": "stepped" },
            { "time": 0.7333, "color": "ffffffff" },
            { "time": 1, "color": "ffffff00" }
          ]
        },
        "star8": {
          "color": [
            { "color": "ffffff00", "curve": "stepped" },
            { "time": 0.1667, "color": "ffffff00" },
            { "time": 0.3333, "color": "ffffffff", "curve": "stepped" },
            { "time": 0.5667, "color": "ffffffff" },
            { "time": 0.8333, "color": "ffffff00" }
          ]
        },
        "star9": {
          "color": [
            { "color": "ffffff00" },
            { "time": 0.1667, "color": "ffffffff", "curve": "stepped" },
            { "time": 0.4, "color": "ffffffff" },
            { "time": 0.6667, "color": "ffffff00" },
            { "time": 0.7, "color": "ffffffff", "curve": "stepped" },
            { "time": 1.1, "color": "ffffffff" },
            { "time": 1.3667, "color": "ffffff00" }
          ]
        },
        "star10": {
          "color": [
            { "color": "ffffff00", "curve": "stepped" },
            { "time": 0.2333, "color": "ffffff00" },
            { "time": 0.3667, "color": "ffffffff", "curve": "stepped" },
            { "time": 0.6333, "color": "ffffffff" },
            { "time": 0.9, "color": "ffffff00" }
          ]
        },
        "star11": {
          "color": [
            { "color": "ffffff00", "curve": "stepped" },
            { "time": 0.5, "color": "ffffff00" },
            { "time": 0.6667, "color": "ffffffff", "curve": "stepped" },
            { "time": 0.9, "color": "ffffffff" },
            { "time": 1.1667, "color": "ffffff00" }
          ]
        },
        "star12": {
          "color": [
            { "color": "ffffff00", "curve": "stepped" },
            { "time": 0.4, "color": "ffffff00" },
            { "time": 0.5667, "color": "ffffffff", "curve": "stepped" },
            { "time": 0.8, "color": "ffffffff" },
            { "time": 1.0667, "color": "ffffff00" }
          ]
        },
        "star13": {
          "color": [
            { "color": "ffffff00", "curve": "stepped" },
            { "time": 0.5, "color": "ffffff00" },
            { "time": 0.6667, "color": "ffffffff", "curve": "stepped" },
            { "time": 0.9, "color": "ffffffff" },
            { "time": 1.1667, "color": "ffffff00" }
          ]
        },
        "star14": {
          "color": [
            { "color": "ffffff00", "curve": "stepped" },
            { "time": 0.3333, "color": "ffffff00" },
            { "time": 0.5, "color": "ffffffff", "curve": "stepped" },
            { "time": 0.7333, "color": "ffffffff" },
            { "time": 1, "color": "ffffff00" }
          ]
        }
      },
      "bones": {
        "rays": {
          "scale": [
            { "x": 0.5, "y": 0.5 },
            { "time": 0.5667, "x": 1.3, "y": 1.3 },
            { "time": 0.6, "x": 0.5, "y": 0.5 },
            { "time": 1.1667, "x": 1.3, "y": 1.3 }
          ]
        },
        "rays2": {
          "scale": [
            { "time": 0.1667, "x": 0.5, "y": 0.5 },
            { "time": 0.7333, "x": 1.3, "y": 1.3 },
            { "time": 0.7667, "x": 0.5, "y": 0.5 },
            { "time": 1.3333, "x": 1.3, "y": 1.3 }
          ]
        },
        "rays3": {
          "scale": [
            { "time": 0.3333, "x": 0.5, "y": 0.5 },
            { "time": 0.9, "x": 1.3, "y": 1.3 }
          ]
        },
        "star": {
          "rotate": [{ "time": 0.1667 }, { "time": 0.8333, "angle": 132 }],
          "translate": [
            { "time": 0.1667 },
            { "time": 0.8333, "x": 106.73, "y": -88.68 }
          ]
        },
        "star2": {
          "rotate": [
            {},
            { "time": 0.6667, "angle": 132 },
            { "time": 0.7 },
            { "time": 1.3667, "angle": 132 }
          ],
          "translate": [
            {},
            { "time": 0.6667, "x": -181.07 },
            { "time": 0.7 },
            { "time": 1.3667, "x": -142.72, "y": 100.37 }
          ]
        },
        "star3": {
          "rotate": [{ "time": 0.2333 }, { "time": 0.9, "angle": 132 }],
          "translate": [
            { "time": 0.2333 },
            { "time": 0.9, "x": -151.34, "y": -91.86 }
          ]
        },
        "star4": {
          "rotate": [{ "time": 0.5 }, { "time": 1.1667, "angle": 132 }],
          "translate": [
            { "time": 0.5, "x": -33.98, "y": 43.54 },
            { "time": 1.1667, "x": -107.26, "y": 136.47 }
          ]
        },
        "star5": {
          "rotate": [{ "time": 0.4 }, { "time": 1.0667, "angle": 132 }],
          "translate": [
            { "time": 0.4 },
            { "time": 1.0667, "x": -184.26, "y": -53.63 }
          ]
        },
        "star6": {
          "rotate": [{ "time": 0.5 }, { "time": 1.1667, "angle": 132 }],
          "translate": [
            { "time": 0.5 },
            { "time": 1.1667, "x": -47.79, "y": -155.05 }
          ]
        },
        "star7": {
          "rotate": [{ "time": 0.3333 }, { "time": 1, "angle": 132 }],
          "translate": [
            { "time": 0.3333 },
            { "time": 1, "x": -149.21, "y": 83.37 }
          ]
        },
        "star8": {
          "rotate": [{ "time": 0.1667 }, { "time": 0.8333, "angle": 132 }],
          "translate": [
            { "time": 0.1667 },
            { "time": 0.8333, "x": -175.76, "y": 76.46 }
          ]
        },
        "star9": {
          "rotate": [
            {},
            { "time": 0.6667, "angle": 132 },
            { "time": 0.7 },
            { "time": 1.3667, "angle": 132 }
          ],
          "translate": [
            {},
            { "time": 0.6667, "x": 75.44, "y": -126.91 },
            { "time": 0.7 },
            { "time": 1.3667, "x": 119.59, "y": -35.57 }
          ]
        },
        "star10": {
          "rotate": [{ "time": 0.2333 }, { "time": 0.9, "angle": 132 }],
          "translate": [
            { "time": 0.2333 },
            { "time": 0.9, "x": 85.56, "y": 116.14 }
          ]
        },
        "star11": {
          "rotate": [{ "time": 0.5 }, { "time": 1.1667, "angle": 132 }],
          "translate": [
            { "time": 0.5, "x": -33.98, "y": 43.54 },
            { "time": 1.1667, "x": 3.16, "y": -145.37 }
          ]
        },
        "star12": {
          "rotate": [{ "time": 0.4 }, { "time": 1.0667, "angle": 132 }],
          "translate": [
            { "time": 0.4 },
            { "time": 1.0667, "x": -3.22, "y": 146.67 }
          ]
        },
        "star13": {
          "rotate": [{ "time": 0.5 }, { "time": 1.1667, "angle": 132 }],
          "translate": [
            { "time": 0.5 },
            { "time": 1.1667, "x": 106.93, "y": 100.46 }
          ]
        },
        "star14": {
          "rotate": [{ "time": 0.3333 }, { "time": 1, "angle": 132 }],
          "translate": [
            { "time": 0.3333 },
            { "time": 1, "x": 122.99, "y": 10.18 }
          ]
        }
      }
    }
  }
}
